ChangeLog
LICENSE
README.rst
VERSION
demo_FrancyWidget.ipynb
setup.cfg
setup.py
binder/environment.yml
binder/postBuild
docs/Makefile
docs/source/conf.py
docs/source/francy_adapter.rst
docs/source/francy_widget.rst
docs/source/index.rst
examples/NDPF4.ipynb
examples/S4.ipynb
examples/WomenMathGenealogy.ipynb
examples/noether.json
francy_widget/__init__.py
francy_widget/calculated_layers.py
francy_widget/francy_adapter.py
francy_widget/francy_widget.py
francy_widget/test.py
francy_widget.egg-info/PKG-INFO
francy_widget.egg-info/SOURCES.txt
francy_widget.egg-info/dependency_links.txt
francy_widget.egg-info/not-zip-safe
francy_widget.egg-info/requires.txt
francy_widget.egg-info/top_level.txt