Metadata-Version: 1.1
Name: francy-widget
Version: 0.3.0
Summary: Francy Widget for representing graphs
Home-page: https://github.com/zerline/francy-widget
Author: Odile Bénassy
Author-email: odile.benassy@u-psud.fr
License: GPLv3+
Keywords: jupyter,widget,graph,francy
Platform: UNKNOWN
Classifier: Development Status :: 3 - Alpha
Classifier: Intended Audience :: Science/Research
Classifier: Topic :: Scientific/Engineering :: Mathematics
Classifier: License :: OSI Approved :: GNU General Public License v3 or later (GPLv3+)
Classifier: Programming Language :: Python :: 2.7
